appdynamics_proxysupport/DISCLAIMER
appdynamics_proxysupport/Welcome.html
appdynamics_proxysupport/__init__.py
appdynamics_proxysupport/readme.txt
appdynamics_proxysupport/release
appdynamics_proxysupport/bin/java
appdynamics_proxysupport/bin/jfr
appdynamics_proxysupport/bin/jjs
appdynamics_proxysupport/bin/jrunscript
appdynamics_proxysupport/bin/keytool
appdynamics_proxysupport/bin/pack200
appdynamics_proxysupport/bin/rmid
appdynamics_proxysupport/bin/rmiregistry
appdynamics_proxysupport/bin/unpack200
appdynamics_proxysupport/conf/logging.properties
appdynamics_proxysupport/conf/net.properties
appdynamics_proxysupport/conf/sound.properties
appdynamics_proxysupport/conf/management/jmxremote.access
appdynamics_proxysupport/conf/management/jmxremote.password.template
appdynamics_proxysupport/conf/management/management.properties
appdynamics_proxysupport/conf/security/java.policy
appdynamics_proxysupport/conf/security/java.security
appdynamics_proxysupport/conf/security/openjsse.security
appdynamics_proxysupport/conf/security/policy/README.txt
appdynamics_proxysupport/conf/security/policy/limited/default_US_export.policy
appdynamics_proxysupport/conf/security/policy/limited/default_local.policy
appdynamics_proxysupport/conf/security/policy/limited/exempt_local.policy
appdynamics_proxysupport/conf/security/policy/unlimited/default_US_export.policy
appdynamics_proxysupport/conf/security/policy/unlimited/default_local.policy
appdynamics_proxysupport/legal/java.base/ADDITIONAL_LICENSE_INFO
appdynamics_proxysupport/legal/java.base/ASSEMBLY_EXCEPTION
appdynamics_proxysupport/legal/java.base/CLASSPATH_EXCEPTION_NOTE
appdynamics_proxysupport/legal/java.base/LICENSE
appdynamics_proxysupport/legal/java.base/aes.md
appdynamics_proxysupport/legal/java.base/asm.md
appdynamics_proxysupport/legal/java.base/c-libutl.md
appdynamics_proxysupport/legal/java.base/cldr.md
appdynamics_proxysupport/legal/java.base/icu.md
appdynamics_proxysupport_linux_x86-11.43.1.dist-info/DESCRIPTION.rst
appdynamics_proxysupport_linux_x86-11.43.1.dist-info/METADATA
appdynamics_proxysupport_linux_x86-11.43.1.dist-info/RECORD
appdynamics_proxysupport_linux_x86-11.43.1.dist-info/WHEEL
appdynamics_proxysupport_linux_x86-11.43.1.dist-info/metadata.json
appdynamics_proxysupport_linux_x86-11.43.1.dist-info/top_level.txt
