Metadata-Version: 2.0
Name: appdynamics-proxysupport-linux-x86
Version: 11.43.1
Summary: Proxysupport for AppDynamics Python agent
Home-page: http://www.appdynamics.com
Author: AppDynamics
Author-email: support@appdynamics.com
License: Proprietary
Platform: UNKNOWN
